.gitignore
CMakeLists.txt
README.md
setup.py
test_cython/__init__.py
test_cython/account.cpp
test_cython/account.hpp
test_cython/approxe.c
test_cython/approxe.pyx
test_cython/dot_cython.c
test_cython/dot_cython.pyx
test_cython/test.py
test_cython/version.py
test_cython_zx.egg-info/PKG-INFO
test_cython_zx.egg-info/SOURCES.txt
test_cython_zx.egg-info/dependency_links.txt
test_cython_zx.egg-info/top_level.txt