Metadata-Version: 2.1
Name: test-cython-zx
Version: 0.0.2
Summary: test_cython infrastructure
Author: test_cythonv
Author-email: info@puyuan.tech
